igloosphinx-0.1.3.dist-info/METADATA
igloosphinx-0.1.3.dist-info/WHEEL
igloosphinx-0.1.3.dist-info/entry_points.txt
igloosphinx-0.1.3.dist-info/licenses/LICENSE
igloosphinx/__init__.py
igloosphinx/cli.py
igloosphinx/convert.py
igloosphinx/inventory.py
igloosphinx-0.1.3.dist-info/RECORD
